belenos/__init__.py
Belenos-0.0.1.dist-info/LICENSE
Belenos-0.0.1.dist-info/METADATA
Belenos-0.0.1.dist-info/WHEEL
Belenos-0.0.1.dist-info/top_level.txt
Belenos-0.0.1.dist-info/RECORD
